oxigen_pipeline/FilterAndClear.py
oxigen_pipeline/__init__.py
oxigen_pipeline/cli.py
oxigen_pipeline/extract.py
oxigen_pipeline/model.py
oxigen_pipeline/pipeline.py
oxigen_pipeline/types_.py
oxigen_pipeline-1.5.0.dist-info/METADATA
oxigen_pipeline-1.5.0.dist-info/WHEEL
oxigen_pipeline-1.5.0.dist-info/entry_points.txt
oxigen_pipeline-1.5.0.dist-info/top_level.txt
oxigen_pipeline-1.5.0.dist-info/RECORD
