Metadata-Version: 2.4
Name: oxigen-pipeline
Version: 1.5.0
Summary: Data pipeline: extract → classify → clean → split -> Model
Author: Daniel Valdez
License: MIT
Requires-Python: >=3.10
Requires-Dist: pandas>=2.3
Requires-Dist: numpy>=1.23
Requires-Dist: scikit-learn<2.0,>=1.3
Requires-Dist: matplotlib>=3.7
Requires-Dist: shap>=0.44
Requires-Dist: xgboost>=1.7
Requires-Dist: lightgbm>=3.3
Requires-Dist: joblib>=1.3
